rizhiy_cfg/__init__.py
rizhiy_cfg/errors.py
rizhiy_cfg/full_key_value.py
rizhiy_cfg/helpers.py
rizhiy_cfg/interfaces.py
rizhiy_cfg/leaf.py
rizhiy_cfg/node.py
rizhiy_cfg/transforms.py
rizhiy_cfg/utils.py
rizhiy_cfg-4.0.1.dist-info/entry_points.txt
rizhiy_cfg-4.0.1.dist-info/LICENSE
rizhiy_cfg-4.0.1.dist-info/WHEEL
rizhiy_cfg-4.0.1.dist-info/METADATA
rizhiy_cfg-4.0.1.dist-info/RECORD
