Metadata-Version: 2.1
Name: rizhiy-cfg
Version: 4.0.1
Summary: Python Configuration System
Author: Vladimir Mikhaylov
Author-email: Artem Vasenin <vasart169@gmail.com>
Maintainer-email: Artem Vasenin <vasart169@gmail.com>
Requires-Python: >=3.9
Requires-Dist: pyyaml
Requires-Dist: rizhiy-cfg[test] ; extra == "dev"
Requires-Dist: black ; extra == "dev"
Requires-Dist: ruff ; extra == "dev"
Requires-Dist: types-pyyaml ; extra == "test"
Requires-Dist: pytest ; extra == "test"
Project-URL: Home, https://github.com/Rizhiy/cfg
Provides-Extra: dev
Provides-Extra: test
